Metadata-Version: 2.1
Name: pscontroll
Version: 2.0
Summary: GTPS Controller via Module
Home-page: https://github.com/iFanpSGTS/PSController_Module
Author: iFanpS
License: MIT
Project-URL: Issue tracker, https://github.com/iFanpSGTS/PSController_Module
Platform: UNKNOWN
Classifier: Development Status :: 5 - Production/Stable
Classifier: License :: OSI Approved :: MIT License
Classifier: Intended Audience :: Developers
Classifier: Natural Language :: English
Classifier: Operating System :: OS Independent
Classifier: Programming Language :: Python :: 3.5
Classifier: Programming Language :: Python :: 3.6
Classifier: Programming Language :: Python :: 3.7
Classifier: Programming Language :: Python :: 3.8
Classifier: Programming Language :: Python :: 3.9
Requires-Python: >=3.5.3
